{
  "fenxi": {
    "cookies": {
      "JSESSIONID": "<REDACTED>",
      "e_token": "<REDACTED>"
    },
    "headers": {
      "mediaids": "<REDACTED>",
      "topic": "<REDACTED>"
    },
    "bootstrap_url": ""
  },
  "505": {
    "cookies": {
      "PHPSESSID": "<REDACTED>",
      "__MANAGE_UID": "<REDACTED>",
      "__MANAGE_USER": "<REDACTED>"
    },
    "headers": {},
    "bootstrap_url": ""
  },
  "pc_web": {
    "cookies": {
      "PHPSESSID": "<REDACTED>"
    },
    "headers": {
      "Bearer": "token=<REDACTED>&chain=0",
      "Origin": "http://<YADMIN_HOST>",
      "Referer": "http://<YADMIN_HOST>/"
    },
    "bootstrap_url": ""
  }
}
